openlr_dereferencer/__init__.py
openlr_dereferencer/_version.py
openlr_dereferencer/decoding/__init__.py
openlr_dereferencer/decoding/candidate.py
openlr_dereferencer/decoding/candidate_functions.py
openlr_dereferencer/decoding/configuration.py
openlr_dereferencer/decoding/error.py
openlr_dereferencer/decoding/line_decoding.py
openlr_dereferencer/decoding/line_location.py
openlr_dereferencer/decoding/path_math.py
openlr_dereferencer/decoding/point_locations.py
openlr_dereferencer/decoding/routes.py
openlr_dereferencer/decoding/scoring.py
openlr_dereferencer/example_sqlite_map/__init__.py
openlr_dereferencer/example_sqlite_map/primitives.py
openlr_dereferencer/maps/__init__.py
openlr_dereferencer/maps/abstract.py
openlr_dereferencer/maps/wgs84.py
openlr_dereferencer/maps/a_star/__init__.py
openlr_dereferencer/maps/a_star/tools.py
openlr_dereferencer/observer/__init__.py
openlr_dereferencer/observer/abstract.py
openlr_dereferencer/observer/simple_observer.py
openlr_dereferencer-1.2.0.dist-info/LICENSE
openlr_dereferencer-1.2.0.dist-info/METADATA
openlr_dereferencer-1.2.0.dist-info/WHEEL
openlr_dereferencer-1.2.0.dist-info/top_level.txt
openlr_dereferencer-1.2.0.dist-info/RECORD
