Metadata-Version: 2.1
Name: openlr-dereferencer
Version: 1.2.0
Summary: OpenLR location dereferencer
Home-page: https://github.com/tomtom-international/openlr-dereferencer-python
Author: Jan Ole Zabel
Author-email: janole.zabel@tomtom.com
License: Apache 2.0
Platform: UNKNOWN
Classifier: Intended Audience :: Developers
Classifier: Natural Language :: English
Classifier: License :: OSI Approved :: Apache Software License
Classifier: Programming Language :: Python
Classifier: Programming Language :: Python :: 3.6
Classifier: Programming Language :: Python :: 3.7
Classifier: Programming Language :: Python :: 3.8
Classifier: Programming Language :: Python :: Implementation :: CPython
Classifier: Programming Language :: Python :: Implementation :: PyPy
Requires-Python: >=3.6
License-File: LICENSE
Requires-Dist: openlr (==1.0.1)
Requires-Dist: geographiclib
Requires-Dist: shapely
